fnum/__init__.py
fnum/__main__.py
fnum/_orchestrator.py
fnum/cli.py
fnum/exceptions.py
fnum/metadata.py
fnum-1.6.0.dist-info/LICENSE
fnum-1.6.0.dist-info/METADATA
fnum-1.6.0.dist-info/WHEEL
fnum-1.6.0.dist-info/entry_points.txt
fnum-1.6.0.dist-info/top_level.txt
fnum-1.6.0.dist-info/RECORD
